{
    "event_ranges": {
        "lefty": [
            {
                "balls": 0,
                "strikes": 0,
                "event": "field_out_fly_ball",
                "decimal_value": 0.14285714285714285,
                "range_start": 0,
                "range_end": 141,
                "count_label": "(0-0)"
            },
            {
                "balls": 0,
                "strikes": 0,
                "event": "field_out_popup",
                "decimal_value": 0.08163265306122448,
                "range_start": 142,
                "range_end": 222,
                "count_label": "(0-0)"
            },
            {
                "balls": 0,
                "strikes": 0,
                "event": "field_out_line_drive",
                "decimal_value": 0.04081632653061224,
                "range_start": 223,
                "range_end": 262,
                "count_label": "(0-0)"
            },
            {
                "balls": 0,
                "strikes": 0,
                "event": "field_out_ground_ball",
                "decimal_value": 0.20408163265306123,
                "range_start": 263,
                "range_end": 466,
                "count_label": "(0-0)"
            },
            {
                "balls": 0,
                "strikes": 0,
                "event": "grounded_into_double_play",
                "decimal_value": 0.061224489795918366,
                "range_start": 467,
                "range_end": 527,
                "count_label": "(0-0)"
            },
            {
                "balls": 0,
                "strikes": 0,
                "event": "force_out",
                "decimal_value": 0.02040816326530612,
                "range_start": 528,
                "range_end": 547,
                "count_label": "(0-0)"
            },
            {
                "balls": 0,
                "strikes": 0,
                "event": "sac_bunt",
                "decimal_value": 0.02040816326530612,
                "range_start": 548,
                "range_end": 567,
                "count_label": "(0-0)"
            },
            {
                "balls": 0,
                "strikes": 0,
                "event": "single",
                "decimal_value": 0.2857142857142857,
                "range_start": 568,
                "range_end": 852,
                "count_label": "(0-0)"
            },
            {
                "balls": 0,
                "strikes": 0,
                "event": "double",
                "decimal_value": 0.08163265306122448,
                "range_start": 853,
                "range_end": 933,
                "count_label": "(0-0)"
            },
            {
                "balls": 0,
                "strikes": 0,
                "event": "home_run",
                "decimal_value": 0.04081632653061224,
                "range_start": 934,
                "range_end": 973,
                "count_label": "(0-0)"
            },
            {
                "balls": 0,
                "strikes": 0,
                "event": "hit_by_pitch",
                "decimal_value": 0.02040816326530612,
                "range_start": 974,
                "range_end": 993,
                "count_label": "(0-0)"
            },
            {
                "balls": 0,
                "strikes": 1,
                "event": "sac_fly",
                "decimal_value": 0.04,
                "range_start": 0,
                "range_end": 39,
                "count_label": "(0-1)"
            },
            {
                "balls": 0,
                "strikes": 1,
                "event": "field_out_fly_ball",
                "decimal_value": 0.2,
                "range_start": 40,
                "range_end": 239,
                "count_label": "(0-1)"
            },
            {
                "balls": 0,
                "strikes": 1,
                "event": "field_out_popup",
                "decimal_value": 0.08,
                "range_start": 240,
                "range_end": 319,
                "count_label": "(0-1)"
            },
            {
                "balls": 0,
                "strikes": 1,
                "event": "field_out_line_drive",
                "decimal_value": 0.08,
                "range_start": 320,
                "range_end": 399,
                "count_label": "(0-1)"
            },
            {
                "balls": 0,
                "strikes": 1,
                "event": "field_out_ground_ball",
                "decimal_value": 0.24,
                "range_start": 400,
                "range_end": 639,
                "count_label": "(0-1)"
            },
            {
                "balls": 0,
                "strikes": 1,
                "event": "double_play",
                "decimal_value": 0.04,
                "range_start": 640,
                "range_end": 679,
                "count_label": "(0-1)"
            },
            {
                "balls": 0,
                "strikes": 1,
                "event": "single",
                "decimal_value": 0.24,
                "range_start": 680,
                "range_end": 919,
                "count_label": "(0-1)"
            },
            {
                "balls": 0,
                "strikes": 1,
                "event": "double",
                "decimal_value": 0.08,
                "range_start": 920,
                "range_end": 999,
                "count_label": "(0-1)"
            },
            {
                "balls": 0,
                "strikes": 2,
                "event": "field_out_fly_ball",
                "decimal_value": 0.14285714285714285,
                "range_start": 0,
                "range_end": 141,
                "count_label": "(0-2)"
            },
            {
                "balls": 0,
                "strikes": 2,
                "event": "field_out_ground_ball",
                "decimal_value": 0.19047619047619047,
                "range_start": 142,
                "range_end": 331,
                "count_label": "(0-2)"
            },
            {
                "balls": 0,
                "strikes": 2,
                "event": "grounded_into_double_play",
                "decimal_value": 0.09523809523809523,
                "range_start": 332,
                "range_end": 426,
                "count_label": "(0-2)"
            },
            {
                "balls": 0,
                "strikes": 2,
                "event": "fielders_choice_out",
                "decimal_value": 0.047619047619047616,
                "range_start": 427,
                "range_end": 473,
                "count_label": "(0-2)"
            },
            {
                "balls": 0,
                "strikes": 2,
                "event": "single",
                "decimal_value": 0.09523809523809523,
                "range_start": 474,
                "range_end": 568,
                "count_label": "(0-2)"
            },
            {
                "balls": 0,
                "strikes": 2,
                "event": "double",
                "decimal_value": 0.047619047619047616,
                "range_start": 569,
                "range_end": 615,
                "count_label": "(0-2)"
            },
            {
                "balls": 0,
                "strikes": 2,
                "event": "hit_by_pitch",
                "decimal_value": 0.14285714285714285,
                "range_start": 616,
                "range_end": 757,
                "count_label": "(0-2)"
            },
            {
                "balls": 0,
                "strikes": 2,
                "event": "strikeout",
                "decimal_value": 0.23809523809523808,
                "range_start": 758,
                "range_end": 995,
                "count_label": "(0-2)"
            },
            {
                "balls": 1,
                "strikes": 0,
                "event": "sac_fly",
                "decimal_value": 0.037037037037037035,
                "range_start": 0,
                "range_end": 36,
                "count_label": "(1-0)"
            },
            {
                "balls": 1,
                "strikes": 0,
                "event": "field_out_fly_ball",
                "decimal_value": 0.4074074074074074,
                "range_start": 37,
                "range_end": 443,
                "count_label": "(1-0)"
            },
            {
                "balls": 1,
                "strikes": 0,
                "event": "field_out_popup",
                "decimal_value": 0.07407407407407407,
                "range_start": 444,
                "range_end": 517,
                "count_label": "(1-0)"
            },
            {
                "balls": 1,
                "strikes": 0,
                "event": "field_out_line_drive",
                "decimal_value": 0.07407407407407407,
                "range_start": 518,
                "range_end": 591,
                "count_label": "(1-0)"
            },
            {
                "balls": 1,
                "strikes": 0,
                "event": "field_out_ground_ball",
                "decimal_value": 0.18518518518518517,
                "range_start": 592,
                "range_end": 776,
                "count_label": "(1-0)"
            },
            {
                "balls": 1,
                "strikes": 0,
                "event": "grounded_into_double_play",
                "decimal_value": 0.037037037037037035,
                "range_start": 777,
                "range_end": 813,
                "count_label": "(1-0)"
            },
            {
                "balls": 1,
                "strikes": 0,
                "event": "double_play",
                "decimal_value": 0.037037037037037035,
                "range_start": 814,
                "range_end": 850,
                "count_label": "(1-0)"
            },
            {
                "balls": 1,
                "strikes": 0,
                "event": "single",
                "decimal_value": 0.07407407407407407,
                "range_start": 851,
                "range_end": 924,
                "count_label": "(1-0)"
            },
            {
                "balls": 1,
                "strikes": 0,
                "event": "double",
                "decimal_value": 0.037037037037037035,
                "range_start": 925,
                "range_end": 961,
                "count_label": "(1-0)"
            },
            {
                "balls": 1,
                "strikes": 0,
                "event": "home_run",
                "decimal_value": 0.037037037037037035,
                "range_start": 962,
                "range_end": 998,
                "count_label": "(1-0)"
            },
            {
                "balls": 1,
                "strikes": 1,
                "event": "field_out_fly_ball",
                "decimal_value": 0.2,
                "range_start": 0,
                "range_end": 199,
                "count_label": "(1-1)"
            },
            {
                "balls": 1,
                "strikes": 1,
                "event": "field_out_popup",
                "decimal_value": 0.15,
                "range_start": 200,
                "range_end": 349,
                "count_label": "(1-1)"
            },
            {
                "balls": 1,
                "strikes": 1,
                "event": "field_out_line_drive",
                "decimal_value": 0.15,
                "range_start": 350,
                "range_end": 499,
                "count_label": "(1-1)"
            },
            {
                "balls": 1,
                "strikes": 1,
                "event": "field_out_ground_ball",
                "decimal_value": 0.2,
                "range_start": 500,
                "range_end": 699,
                "count_label": "(1-1)"
            },
            {
                "balls": 1,
                "strikes": 1,
                "event": "single",
                "decimal_value": 0.15,
                "range_start": 700,
                "range_end": 849,
                "count_label": "(1-1)"
            },
            {
                "balls": 1,
                "strikes": 1,
                "event": "double",
                "decimal_value": 0.05,
                "range_start": 850,
                "range_end": 899,
                "count_label": "(1-1)"
            },
            {
                "balls": 1,
                "strikes": 1,
                "event": "triple",
                "decimal_value": 0.05,
                "range_start": 900,
                "range_end": 949,
                "count_label": "(1-1)"
            },
            {
                "balls": 1,
                "strikes": 1,
                "event": "home_run",
                "decimal_value": 0.05,
                "range_start": 950,
                "range_end": 999,
                "count_label": "(1-1)"
            },
            {
                "balls": 1,
                "strikes": 2,
                "event": "field_out_fly_ball",
                "decimal_value": 0.08695652173913043,
                "range_start": 0,
                "range_end": 85,
                "count_label": "(1-2)"
            },
            {
                "balls": 1,
                "strikes": 2,
                "event": "field_out_popup",
                "decimal_value": 0.043478260869565216,
                "range_start": 86,
                "range_end": 128,
                "count_label": "(1-2)"
            },
            {
                "balls": 1,
                "strikes": 2,
                "event": "field_out_line_drive",
                "decimal_value": 0.06521739130434782,
                "range_start": 129,
                "range_end": 193,
                "count_label": "(1-2)"
            },
            {
                "balls": 1,
                "strikes": 2,
                "event": "field_out_ground_ball",
                "decimal_value": 0.06521739130434782,
                "range_start": 194,
                "range_end": 258,
                "count_label": "(1-2)"
            },
            {
                "balls": 1,
                "strikes": 2,
                "event": "single",
                "decimal_value": 0.06521739130434782,
                "range_start": 259,
                "range_end": 323,
                "count_label": "(1-2)"
            },
            {
                "balls": 1,
                "strikes": 2,
                "event": "double",
                "decimal_value": 0.043478260869565216,
                "range_start": 324,
                "range_end": 366,
                "count_label": "(1-2)"
            },
            {
                "balls": 1,
                "strikes": 2,
                "event": "home_run",
                "decimal_value": 0.021739130434782608,
                "range_start": 367,
                "range_end": 387,
                "count_label": "(1-2)"
            },
            {
                "balls": 1,
                "strikes": 2,
                "event": "hit_by_pitch",
                "decimal_value": 0.021739130434782608,
                "range_start": 388,
                "range_end": 408,
                "count_label": "(1-2)"
            },
            {
                "balls": 1,
                "strikes": 2,
                "event": "strikeout",
                "decimal_value": 0.5869565217391305,
                "range_start": 409,
                "range_end": 994,
                "count_label": "(1-2)"
            },
            {
                "balls": 2,
                "strikes": 0,
                "event": "field_out_fly_ball",
                "decimal_value": 0.25,
                "range_start": 0,
                "range_end": 249,
                "count_label": "(2-0)"
            },
            {
                "balls": 2,
                "strikes": 0,
                "event": "field_out_popup",
                "decimal_value": 0.08333333333333333,
                "range_start": 250,
                "range_end": 332,
                "count_label": "(2-0)"
            },
            {
                "balls": 2,
                "strikes": 0,
                "event": "field_out_ground_ball",
                "decimal_value": 0.16666666666666666,
                "range_start": 333,
                "range_end": 498,
                "count_label": "(2-0)"
            },
            {
                "balls": 2,
                "strikes": 0,
                "event": "force_out",
                "decimal_value": 0.08333333333333333,
                "range_start": 499,
                "range_end": 581,
                "count_label": "(2-0)"
            },
            {
                "balls": 2,
                "strikes": 0,
                "event": "single",
                "decimal_value": 0.16666666666666666,
                "range_start": 582,
                "range_end": 747,
                "count_label": "(2-0)"
            },
            {
                "balls": 2,
                "strikes": 0,
                "event": "double",
                "decimal_value": 0.16666666666666666,
                "range_start": 748,
                "range_end": 913,
                "count_label": "(2-0)"
            },
            {
                "balls": 2,
                "strikes": 0,
                "event": "home_run",
                "decimal_value": 0.08333333333333333,
                "range_start": 914,
                "range_end": 996,
                "count_label": "(2-0)"
            },
            {
                "balls": 2,
                "strikes": 1,
                "event": "field_out_fly_ball",
                "decimal_value": 0.3888888888888889,
                "range_start": 0,
                "range_end": 387,
                "count_label": "(2-1)"
            },
            {
                "balls": 2,
                "strikes": 1,
                "event": "field_out_popup",
                "decimal_value": 0.1111111111111111,
                "range_start": 388,
                "range_end": 498,
                "count_label": "(2-1)"
            },
            {
                "balls": 2,
                "strikes": 1,
                "event": "field_out_ground_ball",
                "decimal_value": 0.1111111111111111,
                "range_start": 499,
                "range_end": 609,
                "count_label": "(2-1)"
            },
            {
                "balls": 2,
                "strikes": 1,
                "event": "grounded_into_double_play",
                "decimal_value": 0.05555555555555555,
                "range_start": 610,
                "range_end": 664,
                "count_label": "(2-1)"
            },
            {
                "balls": 2,
                "strikes": 1,
                "event": "single",
                "decimal_value": 0.1111111111111111,
                "range_start": 665,
                "range_end": 775,
                "count_label": "(2-1)"
            },
            {
                "balls": 2,
                "strikes": 1,
                "event": "double",
                "decimal_value": 0.05555555555555555,
                "range_start": 776,
                "range_end": 830,
                "count_label": "(2-1)"
            },
            {
                "balls": 2,
                "strikes": 1,
                "event": "triple",
                "decimal_value": 0.05555555555555555,
                "range_start": 831,
                "range_end": 885,
                "count_label": "(2-1)"
            },
            {
                "balls": 2,
                "strikes": 1,
                "event": "home_run",
                "decimal_value": 0.1111111111111111,
                "range_start": 886,
                "range_end": 996,
                "count_label": "(2-1)"
            },
            {
                "balls": 2,
                "strikes": 2,
                "event": "field_error",
                "decimal_value": 0.025,
                "range_start": 0,
                "range_end": 24,
                "count_label": "(2-2)"
            },
            {
                "balls": 2,
                "strikes": 2,
                "event": "field_out_fly_ball",
                "decimal_value": 0.1,
                "range_start": 25,
                "range_end": 124,
                "count_label": "(2-2)"
            },
            {
                "balls": 2,
                "strikes": 2,
                "event": "field_out_popup",
                "decimal_value": 0.05,
                "range_start": 125,
                "range_end": 174,
                "count_label": "(2-2)"
            },
            {
                "balls": 2,
                "strikes": 2,
                "event": "field_out_line_drive",
                "decimal_value": 0.05,
                "range_start": 175,
                "range_end": 224,
                "count_label": "(2-2)"
            },
            {
                "balls": 2,
                "strikes": 2,
                "event": "field_out_ground_ball",
                "decimal_value": 0.075,
                "range_start": 225,
                "range_end": 299,
                "count_label": "(2-2)"
            },
            {
                "balls": 2,
                "strikes": 2,
                "event": "force_out",
                "decimal_value": 0.05,
                "range_start": 300,
                "range_end": 349,
                "count_label": "(2-2)"
            },
            {
                "balls": 2,
                "strikes": 2,
                "event": "single",
                "decimal_value": 0.175,
                "range_start": 350,
                "range_end": 524,
                "count_label": "(2-2)"
            },
            {
                "balls": 2,
                "strikes": 2,
                "event": "double",
                "decimal_value": 0.025,
                "range_start": 525,
                "range_end": 549,
                "count_label": "(2-2)"
            },
            {
                "balls": 2,
                "strikes": 2,
                "event": "strikeout",
                "decimal_value": 0.45,
                "range_start": 550,
                "range_end": 999,
                "count_label": "(2-2)"
            },
            {
                "balls": 3,
                "strikes": 0,
                "event": "double",
                "decimal_value": 0.125,
                "range_start": 0,
                "range_end": 124,
                "count_label": "(3-0)"
            },
            {
                "balls": 3,
                "strikes": 0,
                "event": "intent_walk",
                "decimal_value": 0.25,
                "range_start": 125,
                "range_end": 374,
                "count_label": "(3-0)"
            },
            {
                "balls": 3,
                "strikes": 0,
                "event": "walk",
                "decimal_value": 0.625,
                "range_start": 375,
                "range_end": 999,
                "count_label": "(3-0)"
            },
            {
                "balls": 3,
                "strikes": 1,
                "event": "field_out_popup",
                "decimal_value": 0.125,
                "range_start": 0,
                "range_end": 124,
                "count_label": "(3-1)"
            },
            {
                "balls": 3,
                "strikes": 1,
                "event": "field_out_ground_ball",
                "decimal_value": 0.25,
                "range_start": 125,
                "range_end": 374,
                "count_label": "(3-1)"
            },
            {
                "balls": 3,
                "strikes": 1,
                "event": "single",
                "decimal_value": 0.125,
                "range_start": 375,
                "range_end": 499,
                "count_label": "(3-1)"
            },
            {
                "balls": 3,
                "strikes": 1,
                "event": "walk",
                "decimal_value": 0.5,
                "range_start": 500,
                "range_end": 999,
                "count_label": "(3-1)"
            },
            {
                "balls": 3,
                "strikes": 2,
                "event": "field_out_fly_ball",
                "decimal_value": 0.06,
                "range_start": 0,
                "range_end": 59,
                "count_label": "(3-2)"
            },
            {
                "balls": 3,
                "strikes": 2,
                "event": "field_out_popup",
                "decimal_value": 0.06,
                "range_start": 60,
                "range_end": 119,
                "count_label": "(3-2)"
            },
            {
                "balls": 3,
                "strikes": 2,
                "event": "field_out_line_drive",
                "decimal_value": 0.1,
                "range_start": 120,
                "range_end": 219,
                "count_label": "(3-2)"
            },
            {
                "balls": 3,
                "strikes": 2,
                "event": "field_out_ground_ball",
                "decimal_value": 0.1,
                "range_start": 220,
                "range_end": 319,
                "count_label": "(3-2)"
            },
            {
                "balls": 3,
                "strikes": 2,
                "event": "single",
                "decimal_value": 0.04,
                "range_start": 320,
                "range_end": 359,
                "count_label": "(3-2)"
            },
            {
                "balls": 3,
                "strikes": 2,
                "event": "double",
                "decimal_value": 0.04,
                "range_start": 360,
                "range_end": 399,
                "count_label": "(3-2)"
            },
            {
                "balls": 3,
                "strikes": 2,
                "event": "home_run",
                "decimal_value": 0.02,
                "range_start": 400,
                "range_end": 419,
                "count_label": "(3-2)"
            },
            {
                "balls": 3,
                "strikes": 2,
                "event": "walk",
                "decimal_value": 0.26,
                "range_start": 420,
                "range_end": 679,
                "count_label": "(3-2)"
            },
            {
                "balls": 3,
                "strikes": 2,
                "event": "strikeout",
                "decimal_value": 0.32,
                "range_start": 680,
                "range_end": 999,
                "count_label": "(3-2)"
            }
        ],
        "righty": [
            {
                "balls": 0,
                "strikes": 0,
                "event": "field_out_fly_ball",
                "decimal_value": 0.17647058823529413,
                "range_start": 0,
                "range_end": 175,
                "count_label": "(0-0)"
            },
            {
                "balls": 0,
                "strikes": 0,
                "event": "field_out_popup",
                "decimal_value": 0.17647058823529413,
                "range_start": 176,
                "range_end": 351,
                "count_label": "(0-0)"
            },
            {
                "balls": 0,
                "strikes": 0,
                "event": "field_out_line_drive",
                "decimal_value": 0.058823529411764705,
                "range_start": 352,
                "range_end": 409,
                "count_label": "(0-0)"
            },
            {
                "balls": 0,
                "strikes": 0,
                "event": "field_out_ground_ball",
                "decimal_value": 0.23529411764705882,
                "range_start": 410,
                "range_end": 644,
                "count_label": "(0-0)"
            },
            {
                "balls": 0,
                "strikes": 0,
                "event": "grounded_into_double_play",
                "decimal_value": 0.029411764705882353,
                "range_start": 645,
                "range_end": 673,
                "count_label": "(0-0)"
            },
            {
                "balls": 0,
                "strikes": 0,
                "event": "force_out",
                "decimal_value": 0.058823529411764705,
                "range_start": 674,
                "range_end": 731,
                "count_label": "(0-0)"
            },
            {
                "balls": 0,
                "strikes": 0,
                "event": "sac_bunt",
                "decimal_value": 0.029411764705882353,
                "range_start": 732,
                "range_end": 760,
                "count_label": "(0-0)"
            },
            {
                "balls": 0,
                "strikes": 0,
                "event": "single",
                "decimal_value": 0.058823529411764705,
                "range_start": 761,
                "range_end": 818,
                "count_label": "(0-0)"
            },
            {
                "balls": 0,
                "strikes": 0,
                "event": "double",
                "decimal_value": 0.14705882352941177,
                "range_start": 819,
                "range_end": 965,
                "count_label": "(0-0)"
            },
            {
                "balls": 0,
                "strikes": 0,
                "event": "home_run",
                "decimal_value": 0.029411764705882353,
                "range_start": 966,
                "range_end": 994,
                "count_label": "(0-0)"
            },
            {
                "balls": 0,
                "strikes": 1,
                "event": "field_error",
                "decimal_value": 0.05263157894736842,
                "range_start": 0,
                "range_end": 51,
                "count_label": "(0-1)"
            },
            {
                "balls": 0,
                "strikes": 1,
                "event": "field_out_fly_ball",
                "decimal_value": 0.21052631578947367,
                "range_start": 52,
                "range_end": 261,
                "count_label": "(0-1)"
            },
            {
                "balls": 0,
                "strikes": 1,
                "event": "field_out_popup",
                "decimal_value": 0.05263157894736842,
                "range_start": 262,
                "range_end": 313,
                "count_label": "(0-1)"
            },
            {
                "balls": 0,
                "strikes": 1,
                "event": "field_out_ground_ball",
                "decimal_value": 0.47368421052631576,
                "range_start": 314,
                "range_end": 786,
                "count_label": "(0-1)"
            },
            {
                "balls": 0,
                "strikes": 1,
                "event": "force_out",
                "decimal_value": 0.05263157894736842,
                "range_start": 787,
                "range_end": 838,
                "count_label": "(0-1)"
            },
            {
                "balls": 0,
                "strikes": 1,
                "event": "single",
                "decimal_value": 0.10526315789473684,
                "range_start": 839,
                "range_end": 943,
                "count_label": "(0-1)"
            },
            {
                "balls": 0,
                "strikes": 1,
                "event": "hit_by_pitch",
                "decimal_value": 0.05263157894736842,
                "range_start": 944,
                "range_end": 995,
                "count_label": "(0-1)"
            },
            {
                "balls": 0,
                "strikes": 2,
                "event": "field_out_fly_ball",
                "decimal_value": 0.02702702702702703,
                "range_start": 0,
                "range_end": 26,
                "count_label": "(0-2)"
            },
            {
                "balls": 0,
                "strikes": 2,
                "event": "field_out_popup",
                "decimal_value": 0.05405405405405406,
                "range_start": 27,
                "range_end": 80,
                "count_label": "(0-2)"
            },
            {
                "balls": 0,
                "strikes": 2,
                "event": "field_out_ground_ball",
                "decimal_value": 0.13513513513513514,
                "range_start": 81,
                "range_end": 215,
                "count_label": "(0-2)"
            },
            {
                "balls": 0,
                "strikes": 2,
                "event": "double_play",
                "decimal_value": 0.02702702702702703,
                "range_start": 216,
                "range_end": 242,
                "count_label": "(0-2)"
            },
            {
                "balls": 0,
                "strikes": 2,
                "event": "single",
                "decimal_value": 0.02702702702702703,
                "range_start": 243,
                "range_end": 269,
                "count_label": "(0-2)"
            },
            {
                "balls": 0,
                "strikes": 2,
                "event": "double",
                "decimal_value": 0.05405405405405406,
                "range_start": 270,
                "range_end": 323,
                "count_label": "(0-2)"
            },
            {
                "balls": 0,
                "strikes": 2,
                "event": "hit_by_pitch",
                "decimal_value": 0.05405405405405406,
                "range_start": 324,
                "range_end": 377,
                "count_label": "(0-2)"
            },
            {
                "balls": 0,
                "strikes": 2,
                "event": "strikeout",
                "decimal_value": 0.5945945945945946,
                "range_start": 378,
                "range_end": 971,
                "count_label": "(0-2)"
            },
            {
                "balls": 0,
                "strikes": 2,
                "event": "truncated_pa",
                "decimal_value": 0.02702702702702703,
                "range_start": 972,
                "range_end": 998,
                "count_label": "(0-2)"
            },
            {
                "balls": 1,
                "strikes": 0,
                "event": "field_error",
                "decimal_value": 0.07142857142857142,
                "range_start": 0,
                "range_end": 70,
                "count_label": "(1-0)"
            },
            {
                "balls": 1,
                "strikes": 0,
                "event": "field_out_fly_ball",
                "decimal_value": 0.35714285714285715,
                "range_start": 71,
                "range_end": 427,
                "count_label": "(1-0)"
            },
            {
                "balls": 1,
                "strikes": 0,
                "event": "field_out_popup",
                "decimal_value": 0.07142857142857142,
                "range_start": 428,
                "range_end": 498,
                "count_label": "(1-0)"
            },
            {
                "balls": 1,
                "strikes": 0,
                "event": "field_out_ground_ball",
                "decimal_value": 0.2857142857142857,
                "range_start": 499,
                "range_end": 783,
                "count_label": "(1-0)"
            },
            {
                "balls": 1,
                "strikes": 0,
                "event": "single",
                "decimal_value": 0.21428571428571427,
                "range_start": 784,
                "range_end": 997,
                "count_label": "(1-0)"
            },
            {
                "balls": 1,
                "strikes": 1,
                "event": "field_out_fly_ball",
                "decimal_value": 0.16666666666666666,
                "range_start": 0,
                "range_end": 165,
                "count_label": "(1-1)"
            },
            {
                "balls": 1,
                "strikes": 1,
                "event": "field_out_popup",
                "decimal_value": 0.16666666666666666,
                "range_start": 166,
                "range_end": 331,
                "count_label": "(1-1)"
            },
            {
                "balls": 1,
                "strikes": 1,
                "event": "field_out_ground_ball",
                "decimal_value": 0.3333333333333333,
                "range_start": 332,
                "range_end": 664,
                "count_label": "(1-1)"
            },
            {
                "balls": 1,
                "strikes": 1,
                "event": "grounded_into_double_play",
                "decimal_value": 0.16666666666666666,
                "range_start": 665,
                "range_end": 830,
                "count_label": "(1-1)"
            },
            {
                "balls": 1,
                "strikes": 1,
                "event": "force_out",
                "decimal_value": 0.16666666666666666,
                "range_start": 831,
                "range_end": 996,
                "count_label": "(1-1)"
            },
            {
                "balls": 1,
                "strikes": 2,
                "event": "field_out_fly_ball",
                "decimal_value": 0.06382978723404255,
                "range_start": 0,
                "range_end": 62,
                "count_label": "(1-2)"
            },
            {
                "balls": 1,
                "strikes": 2,
                "event": "field_out_line_drive",
                "decimal_value": 0.02127659574468085,
                "range_start": 63,
                "range_end": 83,
                "count_label": "(1-2)"
            },
            {
                "balls": 1,
                "strikes": 2,
                "event": "field_out_ground_ball",
                "decimal_value": 0.1276595744680851,
                "range_start": 84,
                "range_end": 210,
                "count_label": "(1-2)"
            },
            {
                "balls": 1,
                "strikes": 2,
                "event": "grounded_into_double_play",
                "decimal_value": 0.0425531914893617,
                "range_start": 211,
                "range_end": 252,
                "count_label": "(1-2)"
            },
            {
                "balls": 1,
                "strikes": 2,
                "event": "single",
                "decimal_value": 0.19148936170212766,
                "range_start": 253,
                "range_end": 443,
                "count_label": "(1-2)"
            },
            {
                "balls": 1,
                "strikes": 2,
                "event": "double",
                "decimal_value": 0.06382978723404255,
                "range_start": 444,
                "range_end": 506,
                "count_label": "(1-2)"
            },
            {
                "balls": 1,
                "strikes": 2,
                "event": "hit_by_pitch",
                "decimal_value": 0.02127659574468085,
                "range_start": 507,
                "range_end": 527,
                "count_label": "(1-2)"
            },
            {
                "balls": 1,
                "strikes": 2,
                "event": "strikeout",
                "decimal_value": 0.44680851063829785,
                "range_start": 528,
                "range_end": 973,
                "count_label": "(1-2)"
            },
            {
                "balls": 2,
                "strikes": 0,
                "event": "field_out_fly_ball",
                "decimal_value": 0.5,
                "range_start": 0,
                "range_end": 499,
                "count_label": "(2-0)"
            },
            {
                "balls": 2,
                "strikes": 0,
                "event": "field_out_popup",
                "decimal_value": 0.16666666666666666,
                "range_start": 500,
                "range_end": 665,
                "count_label": "(2-0)"
            },
            {
                "balls": 2,
                "strikes": 0,
                "event": "grounded_into_double_play",
                "decimal_value": 0.16666666666666666,
                "range_start": 666,
                "range_end": 831,
                "count_label": "(2-0)"
            },
            {
                "balls": 2,
                "strikes": 0,
                "event": "single",
                "decimal_value": 0.16666666666666666,
                "range_start": 832,
                "range_end": 997,
                "count_label": "(2-0)"
            },
            {
                "balls": 2,
                "strikes": 1,
                "event": "field_out_fly_ball",
                "decimal_value": 0.36363636363636365,
                "range_start": 0,
                "range_end": 362,
                "count_label": "(2-1)"
            },
            {
                "balls": 2,
                "strikes": 1,
                "event": "field_out_ground_ball",
                "decimal_value": 0.18181818181818182,
                "range_start": 363,
                "range_end": 543,
                "count_label": "(2-1)"
            },
            {
                "balls": 2,
                "strikes": 1,
                "event": "force_out",
                "decimal_value": 0.09090909090909091,
                "range_start": 544,
                "range_end": 633,
                "count_label": "(2-1)"
            },
            {
                "balls": 2,
                "strikes": 1,
                "event": "single",
                "decimal_value": 0.2727272727272727,
                "range_start": 634,
                "range_end": 905,
                "count_label": "(2-1)"
            },
            {
                "balls": 2,
                "strikes": 1,
                "event": "triple",
                "decimal_value": 0.09090909090909091,
                "range_start": 906,
                "range_end": 995,
                "count_label": "(2-1)"
            },
            {
                "balls": 2,
                "strikes": 2,
                "event": "sac_fly",
                "decimal_value": 0.025,
                "range_start": 0,
                "range_end": 24,
                "count_label": "(2-2)"
            },
            {
                "balls": 2,
                "strikes": 2,
                "event": "field_out_fly_ball",
                "decimal_value": 0.125,
                "range_start": 25,
                "range_end": 149,
                "count_label": "(2-2)"
            },
            {
                "balls": 2,
                "strikes": 2,
                "event": "field_out_popup",
                "decimal_value": 0.025,
                "range_start": 150,
                "range_end": 174,
                "count_label": "(2-2)"
            },
            {
                "balls": 2,
                "strikes": 2,
                "event": "field_out_line_drive",
                "decimal_value": 0.025,
                "range_start": 175,
                "range_end": 199,
                "count_label": "(2-2)"
            },
            {
                "balls": 2,
                "strikes": 2,
                "event": "field_out_ground_ball",
                "decimal_value": 0.1,
                "range_start": 200,
                "range_end": 299,
                "count_label": "(2-2)"
            },
            {
                "balls": 2,
                "strikes": 2,
                "event": "fielders_choice",
                "decimal_value": 0.025,
                "range_start": 300,
                "range_end": 324,
                "count_label": "(2-2)"
            },
            {
                "balls": 2,
                "strikes": 2,
                "event": "single",
                "decimal_value": 0.025,
                "range_start": 325,
                "range_end": 349,
                "count_label": "(2-2)"
            },
            {
                "balls": 2,
                "strikes": 2,
                "event": "triple",
                "decimal_value": 0.025,
                "range_start": 350,
                "range_end": 374,
                "count_label": "(2-2)"
            },
            {
                "balls": 2,
                "strikes": 2,
                "event": "home_run",
                "decimal_value": 0.025,
                "range_start": 375,
                "range_end": 399,
                "count_label": "(2-2)"
            },
            {
                "balls": 2,
                "strikes": 2,
                "event": "hit_by_pitch",
                "decimal_value": 0.025,
                "range_start": 400,
                "range_end": 424,
                "count_label": "(2-2)"
            },
            {
                "balls": 2,
                "strikes": 2,
                "event": "strikeout",
                "decimal_value": 0.575,
                "range_start": 425,
                "range_end": 999,
                "count_label": "(2-2)"
            },
            {
                "balls": 3,
                "strikes": 0,
                "event": "intent_walk",
                "decimal_value": 0.14285714285714285,
                "range_start": 0,
                "range_end": 141,
                "count_label": "(3-0)"
            },
            {
                "balls": 3,
                "strikes": 0,
                "event": "walk",
                "decimal_value": 0.8571428571428571,
                "range_start": 142,
                "range_end": 998,
                "count_label": "(3-0)"
            },
            {
                "balls": 3,
                "strikes": 1,
                "event": "field_out_fly_ball",
                "decimal_value": 0.125,
                "range_start": 0,
                "range_end": 124,
                "count_label": "(3-1)"
            },
            {
                "balls": 3,
                "strikes": 1,
                "event": "field_out_popup",
                "decimal_value": 0.125,
                "range_start": 125,
                "range_end": 249,
                "count_label": "(3-1)"
            },
            {
                "balls": 3,
                "strikes": 1,
                "event": "field_out_line_drive",
                "decimal_value": 0.125,
                "range_start": 250,
                "range_end": 374,
                "count_label": "(3-1)"
            },
            {
                "balls": 3,
                "strikes": 1,
                "event": "field_out_ground_ball",
                "decimal_value": 0.125,
                "range_start": 375,
                "range_end": 499,
                "count_label": "(3-1)"
            },
            {
                "balls": 3,
                "strikes": 1,
                "event": "double_play",
                "decimal_value": 0.125,
                "range_start": 500,
                "range_end": 624,
                "count_label": "(3-1)"
            },
            {
                "balls": 3,
                "strikes": 1,
                "event": "walk",
                "decimal_value": 0.25,
                "range_start": 625,
                "range_end": 874,
                "count_label": "(3-1)"
            },
            {
                "balls": 3,
                "strikes": 1,
                "event": "hit_by_pitch",
                "decimal_value": 0.125,
                "range_start": 875,
                "range_end": 999,
                "count_label": "(3-1)"
            },
            {
                "balls": 3,
                "strikes": 2,
                "event": "field_out_fly_ball",
                "decimal_value": 0.0625,
                "range_start": 0,
                "range_end": 61,
                "count_label": "(3-2)"
            },
            {
                "balls": 3,
                "strikes": 2,
                "event": "field_out_popup",
                "decimal_value": 0.0625,
                "range_start": 62,
                "range_end": 123,
                "count_label": "(3-2)"
            },
            {
                "balls": 3,
                "strikes": 2,
                "event": "single",
                "decimal_value": 0.15625,
                "range_start": 124,
                "range_end": 279,
                "count_label": "(3-2)"
            },
            {
                "balls": 3,
                "strikes": 2,
                "event": "double",
                "decimal_value": 0.03125,
                "range_start": 280,
                "range_end": 310,
                "count_label": "(3-2)"
            },
            {
                "balls": 3,
                "strikes": 2,
                "event": "walk",
                "decimal_value": 0.375,
                "range_start": 311,
                "range_end": 685,
                "count_label": "(3-2)"
            },
            {
                "balls": 3,
                "strikes": 2,
                "event": "strikeout",
                "decimal_value": 0.3125,
                "range_start": 686,
                "range_end": 997,
                "count_label": "(3-2)"
            }
        ],
        "lefty_bb_type_summary": [
            {
                "bb_type": "fly_ball",
                "count": 51
            },
            {
                "bb_type": "ground_ball",
                "count": 46
            },
            {
                "bb_type": "line_drive",
                "count": 19
            },
            {
                "bb_type": "popup",
                "count": 22
            }
        ],
        "righty_bb_type_summary": [
            {
                "bb_type": "fly_ball",
                "count": 35
            },
            {
                "bb_type": "ground_ball",
                "count": 41
            },
            {
                "bb_type": "line_drive",
                "count": 5
            },
            {
                "bb_type": "popup",
                "count": 16
            }
        ]
    },
    "count_frequencies": [
        {
            "count_label": "(0-0)",
            "range_start": 0,
            "range_end": 140
        },
        {
            "count_label": "(0-1)",
            "range_start": 141,
            "range_end": 215
        },
        {
            "count_label": "(0-2)",
            "range_start": 216,
            "range_end": 314
        },
        {
            "count_label": "(1-0)",
            "range_start": 315,
            "range_end": 384
        },
        {
            "count_label": "(1-1)",
            "range_start": 385,
            "range_end": 428
        },
        {
            "count_label": "(1-2)",
            "range_start": 429,
            "range_end": 586
        },
        {
            "count_label": "(2-0)",
            "range_start": 587,
            "range_end": 616
        },
        {
            "count_label": "(2-1)",
            "range_start": 617,
            "range_end": 665
        },
        {
            "count_label": "(2-2)",
            "range_start": 666,
            "range_end": 801
        },
        {
            "count_label": "(3-0)",
            "range_start": 802,
            "range_end": 826
        },
        {
            "count_label": "(3-1)",
            "range_start": 827,
            "range_end": 853
        },
        {
            "count_label": "(3-2)",
            "range_start": 854,
            "range_end": 993
        }
    ],
    "distinct_events": [
        "double",
        "strikeout",
        "single",
        "field_out",
        "force_out",
        "double_play",
        "walk",
        "grounded_into_double_play",
        "sac_fly",
        "home_run",
        "sac_bunt",
        "triple",
        "hit_by_pitch",
        "intent_walk",
        "truncated_pa",
        "field_error",
        "fielders_choice",
        "fielders_choice_out"
    ]
}